trovares_connector/__init__.py
trovares_connector/common.py
trovares_connector/odbc.py
trovares_connector/neo4j_connector/__init__.py
trovares_connector/neo4j_connector/neo4j_connector.py
trovares_connector/neo4j_connector/query_translator.py
trovares_connector/neo4j_connector/frontend/CypherLexer.py
trovares_connector/neo4j_connector/frontend/CypherListener.py
trovares_connector/neo4j_connector/frontend/CypherParser.py
trovares_connector/neo4j_connector/frontend/CypherVisitor.py
trovares_connector/neo4j_connector/frontend/__init__.py
trovares_connector-2.6.4.dist-info/LICENSE
trovares_connector-2.6.4.dist-info/METADATA
trovares_connector-2.6.4.dist-info/WHEEL
trovares_connector-2.6.4.dist-info/top_level.txt
trovares_connector-2.6.4.dist-info/RECORD
