Metadata-Version: 2.2
Name: trovares_connector
Version: 2.6.4
Summary: DEPRECATED: Use `xgt-connector` instead. This package has been renamed.
Home-page: http://www.trovares.com/
Author: Trovares, Inc.
Author-email: support@trovares.com
License: apache2
Project-URL: Documentation, https://trovares.github.io/trovares_connector/
Project-URL: Repository, https://github.com/trovares/trovares_connector
Project-URL: Changelog, https://github.com/trovares/trovares_connector/blob/main/RELEASE.rst
Keywords: Neo4j Trovares xGT cypher ODBC database
Classifier: Development Status :: 7 - Inactive
Classifier: License :: OSI Approved :: Apache Software License
Classifier: Operating System :: OS Independent
Classifier: Programming Language :: Python :: 3
Classifier: Programming Language :: Python :: 3.9
Classifier: Programming Language :: Python :: 3.10
Classifier: Programming Language :: Python :: 3.11
Classifier: Programming Language :: Python :: 3.12
Classifier: Programming Language :: Python :: 3.13
Classifier: Topic :: Database
Classifier: Topic :: Database
Classifier: Topic :: Database :: Front-Ends
Requires-Python: >=3.7
License-File: LICENSE
Requires-Dist: neo4j>=4.4.1
Requires-Dist: xgt>=1.14.0
Requires-Dist: pyarrow>=7.0.0
Requires-Dist: antlr4-python3-runtime>=4.10
Requires-Dist: xgt_connector>=2.6.4
Provides-Extra: odbc
Requires-Dist: arrow_odbc==0.2.0; extra == "odbc"
Requires-Dist: pandas; extra == "odbc"
